pickomino_env/__init__.py
pickomino_env/pickomino.py
pickomino_env/py.typed
pickomino_env/modules/__init__.py
pickomino_env/modules/action_checker.py
pickomino_env/modules/bot.py
pickomino_env/modules/constants.py
pickomino_env/modules/dice.py
pickomino_env/modules/game.py
pickomino_env/modules/player.py
pickomino_env/modules/renderer.py
pickomino_env/modules/rule_checker.py
pickomino_env/modules/tiles.py
pickomino_env-1.1.1.dist-info/LICENSE
pickomino_env-1.1.1.dist-info/METADATA
pickomino_env-1.1.1.dist-info/WHEEL
pickomino_env-1.1.1.dist-info/top_level.txt
pickomino_env-1.1.1.dist-info/RECORD
