Metadata-Version: 2.1
Name: pickomino-env
Version: 1.1.1
Summary: Pickomino (Heckmeck) Gymnasium environment
Author: Jarl and Robin
Requires-Python: <3.14,>=3.8
License-File: LICENSE
Requires-Dist: gymnasium<2.0.0,>=1.1.1
Requires-Dist: numpy<3.0.0,>=1.24.0
Requires-Dist: pygame<3.0.0,>=2.6.1
Requires-Dist: setuptools<81
Requires-Dist: importlib-resources>=5.0; python_version < "3.9"
Provides-Extra: dev
Requires-Dist: pytest<9.0.0,>=8.3.5; extra == "dev"
Requires-Dist: pytest-cov<6.0,>=5.0; extra == "dev"
Requires-Dist: pytest-timeout<3.0,>=2.0; extra == "dev"
Requires-Dist: matplotlib<4.0,>=3.0; extra == "dev"
Requires-Dist: stable-baselines3<3.0,>=2.3.0; extra == "dev"
Provides-Extra: test
Requires-Dist: pytest<9.0.0,>=8.3.5; extra == "test"
Requires-Dist: pytest-cov<6.0,>=5.0; extra == "test"
